peng_ui/__init__.py
peng_ui/container.py
peng_ui/utils.py
peng_ui/viewer.py
peng_ui/elements/__init__.py
peng_ui/elements/base_element.py
peng_ui/elements/button.py
peng_ui/elements/edit_field.py
peng_ui/elements/label.py
peng_ui/elements/text_field.py
peng_ui-0.3.5.dist-info/licenses/LICENSE
scripts/main.py
peng_ui-0.3.5.dist-info/METADATA
peng_ui-0.3.5.dist-info/WHEEL
peng_ui-0.3.5.dist-info/top_level.txt
peng_ui-0.3.5.dist-info/RECORD
