Metadata-Version: 2.4
Name: peng_ui
Version: 0.3.5
Summary: Basic UI components for a Pygame environment.
Author-email: Bruno Schilling <bruno.schilling@protonmail.ch>
License-Expression: MIT
Project-URL: Repository, https://github.com/Bluemi/peng_ui
Requires-Python: >=3.11
License-File: LICENSE
Requires-Dist: pygame>=2.6
Provides-Extra: dev
Requires-Dist: pytest; extra == "dev"
Requires-Dist: build; extra == "dev"
Requires-Dist: twine; extra == "dev"
Dynamic: license-file
